go_dutch/__init__.py
go_dutch/group.py
go_dutch-1.0.2.dist-info/LICENSE
go_dutch-1.0.2.dist-info/METADATA
go_dutch-1.0.2.dist-info/WHEEL
go_dutch-1.0.2.dist-info/top_level.txt
go_dutch-1.0.2.dist-info/RECORD
