Metadata-Version: 2.1
Name: go-dutch
Version: 1.0.2
Summary: Library for simplifying shared costs
Home-page: https://github.com/cyu5/go-dutch
Author: Chengjia Yu, Sanjiv Pradhanang
Author-email: cyu27182@gmail.com, pradhanang.sanjiv@gmail.com
License: UNKNOWN
Project-URL: Bug Tracker, https://github.com/cyu5/go-dutch/issues
Platform: UNKNOWN
Classifier: Programming Language :: Python :: 3
Classifier: License :: OSI Approved :: MIT License
Classifier: Operating System :: OS Independent
Requires-Python: >=3.6
License-File: LICENSE
